pytest_tmpfs/__init__.py
pytest_tmpfs/fs.py
pytest_tmpfs/plugin.py
tests/__init__.py
tests/conftest.py
tests/test_tmpfs.py
pytest_tmpfs-0.1.4.dist-info/LICENSE
pytest_tmpfs-0.1.4.dist-info/METADATA
pytest_tmpfs-0.1.4.dist-info/WHEEL
pytest_tmpfs-0.1.4.dist-info/entry_points.txt
pytest_tmpfs-0.1.4.dist-info/top_level.txt
pytest_tmpfs-0.1.4.dist-info/RECORD
